whereismyip/__init__.py
whereismyip-0.1.0.dist-info/METADATA
whereismyip-0.1.0.dist-info/WHEEL
whereismyip-0.1.0.dist-info/top_level.txt
whereismyip-0.1.0.dist-info/RECORD
