Metadata-Version: 2.4
Name: whereismyip
Version: 0.1.0
Summary: A simple Python library that queries multiple geolocation services until one succeeds.
Author-email: Al Sweigart <al@inventwithpython.com>
License: GPL-3.0
Requires-Python: >=3.6
